README.rst
setup.py
qb/__init__.py
qb/geo/__init__.py
qb/geo/area.py
qb/geo/distance.py
qb/pako/__init__.py
qb/statistics/__init__.py
qb/statistics/correlation_analysis.py
qb/statistics/error_analysis.py
qb/statistics/tool.py
qb/statistics/variance_analysis.py
queensbarry.egg-info/PKG-INFO
queensbarry.egg-info/SOURCES.txt
queensbarry.egg-info/dependency_links.txt
queensbarry.egg-info/requires.txt
queensbarry.egg-info/top_level.txt